relearn/__init__.py
relearn/agent.py
relearn/environment.py
relearn/mdp.py
relearn-0.1.2.dist-info/LICENSE.md
relearn-0.1.2.dist-info/METADATA
relearn-0.1.2.dist-info/WHEEL
relearn-0.1.2.dist-info/RECORD
