Metadata-Version: 2.1
Name: relearn
Version: 0.1.2
Summary: A package for reinforcement learning (RL) development, featuring classes for Markov Decision Processes (MDPs), agents, and environments. Ideal for creating custom RL environments and experimenting with algorithms. Suitable for researchers, educators, and developers seeking to explore or implement RL applications.
License: GPL-3.0-only
Author: eliroc98
Author-email: elisabetta.rocchetti0@gmail.com
Requires-Python: >=3.9,<3.13
Classifier: License :: OSI Approved :: GNU General Public License v3 (GPLv3)
Classifier: Programming Language :: Python :: 3
Classifier: Programming Language :: Python :: 3.9
Classifier: Programming Language :: Python :: 3.10
Classifier: Programming Language :: Python :: 3.11
Requires-Dist: numpy (>=1.26.4,<2.0.0)
